lektor_npm_support.py
lektor_npm_support-0.1.dist-info/DESCRIPTION.rst
lektor_npm_support-0.1.dist-info/METADATA
lektor_npm_support-0.1.dist-info/RECORD
lektor_npm_support-0.1.dist-info/WHEEL
lektor_npm_support-0.1.dist-info/entry_points.txt
lektor_npm_support-0.1.dist-info/metadata.json
lektor_npm_support-0.1.dist-info/top_level.txt
tests/conftest.py
tests/test_plugin.py
