Metadata-Version: 2.0
Name: lektor-npm-support
Version: 0.1
Summary: Adds support for using npm/yarn to build assets in Lektor
Home-page: http://github.com/sterin/lektor-npm-support
Author: Baruch Sterin
Author-email: lektor-npm-support@bsterin.com
License: BSD
Platform: UNKNOWN
Requires-Dist: future
Provides-Extra: test
Requires-Dist: lektor; extra == 'test'
Requires-Dist: pytest; extra == 'test'
Requires-Dist: pytest-cov; extra == 'test'
Requires-Dist: pytest-mock; extra == 'test'
